weathergrabber/__init__.py
weathergrabber/cli.py
weathergrabber/core.py
weathergrabber/weathergrabber_application.py
weathergrabber/adapter/client/weather_api.py
weathergrabber/adapter/client/weather_search_api.py
weathergrabber/adapter/tty/console_tty.py
weathergrabber/adapter/tty/json_tty.py
weathergrabber/adapter/tty/waybar_tty.py
weathergrabber/domain/air_quality_index.py
weathergrabber/domain/city_location.py
weathergrabber/domain/color.py
weathergrabber/domain/current_conditions.py
weathergrabber/domain/daily_predictions.py
weathergrabber/domain/day_night.py
weathergrabber/domain/forecast.py
weathergrabber/domain/health_activities.py
weathergrabber/domain/hourly_predictions.py
weathergrabber/domain/label_value.py
weathergrabber/domain/moon_phase.py
weathergrabber/domain/moon_phase_enum.py
weathergrabber/domain/precipitation.py
weathergrabber/domain/search.py
weathergrabber/domain/sunrise_sunset.py
weathergrabber/domain/temperature_hight_low.py
weathergrabber/domain/timestamp.py
weathergrabber/domain/today_details.py
weathergrabber/domain/uv_index.py
weathergrabber/domain/weather_icon_enum.py
weathergrabber/domain/wind.py
weathergrabber/domain/adapter/icon_enum.py
weathergrabber/domain/adapter/output_enum.py
weathergrabber/domain/adapter/params.py
weathergrabber/domain/adapter/mapper/air_quality_index_mapper.py
weathergrabber/domain/adapter/mapper/city_location_mapper.py
weathergrabber/domain/adapter/mapper/color_mapper.py
weathergrabber/domain/adapter/mapper/current_conditions_mapper.py
weathergrabber/domain/adapter/mapper/daily_predictions_mapper.py
weathergrabber/domain/adapter/mapper/day_night_mapper.py
weathergrabber/domain/adapter/mapper/forecast_mapper.py
weathergrabber/domain/adapter/mapper/health_activities_mapper.py
weathergrabber/domain/adapter/mapper/hourly_predictions_mapper.py
weathergrabber/domain/adapter/mapper/label_value_mapper.py
weathergrabber/domain/adapter/mapper/moon_phase_mapper.py
weathergrabber-0.0.6.dist-info/licenses/LICENSE
weathergrabber-0.0.6.dist-info/METADATA
weathergrabber-0.0.6.dist-info/WHEEL
weathergrabber-0.0.6.dist-info/entry_points.txt
weathergrabber-0.0.6.dist-info/top_level.txt
weathergrabber-0.0.6.dist-info/RECORD
