Metadata-Version: 2.4
Name: weathergrabber
Version: 0.0.6
Summary: A grabber for weather.com data with various output formats.
Author-email: Carlos Anselmo Mendes Junior <cjuniorfox@gmail.com>
License: MIT
Project-URL: homepage, https://github.com/cjuniorfox/weather
Project-URL: repository, https://github.com/cjuniorfox/weather
Requires-Python: >=3.12
License-File: LICENSE
Requires-Dist: pyquery>=1.4.3
Requires-Dist: requests>=2.32.4
Dynamic: license-file
